{
  "ocaml_sorted": "{\n  \"diagnostics\": [\n    {\n      \"audit\": {\n        \"audit_id\": \"cli/20251110T081149Z-d1fb623#0\",\n        \"change_set\": {\n          \"items\": [\n            {\n              \"args\": [\n                \"/Users/dolphilia/github/kestrel/compiler/ocaml/_build/install/default/bin/remlc\",\n                \"--packrat\",\n                \"--format\",\n                \"json\",\n                \"--json-mode\",\n                \"compact\",\n                \"--emit-parse-debug\",\n                \"/Users/dolphilia/github/kestrel/reports/dual-write/front-end/w4-diagnostics/20280418-w4-diag-effects-r3/stream_pending_resume/ocaml.parse-debug.json\",\n                \"--left-recursion\",\n                \"off\",\n                \"--streaming\",\n                \"--stream-resume-hint\",\n                \"diag-w4\",\n                \"--stream-flow-policy\",\n                \"auto\",\n                \"--stream-demand-min-bytes\",\n                \"4\",\n                \"--stream-demand-preferred-bytes\",\n                \"8\",\n                \"--stream-flow-max-lag\",\n                \"8192\",\n                \"/Users/dolphilia/github/kestrel/reports/dual-write/front-end/w4-diagnostics/20280418-w4-diag-effects-r3/stream_pending_resume/input.reml\"\n              ],\n              \"command\": \"remlc\",\n              \"kind\": \"cli-command\"\n            },\n            {\n              \"kind\": \"input\",\n              \"path\": \"input.reml\",\n              \"target\": \"x86_64-linux\"\n            },\n            {\n              \"kind\": \"outputs\",\n              \"values\": [\n                \"emit_parse_debug\"\n              ]\n            }\n          ],\n          \"origin\": \"cli\",\n          \"policy\": \"phase2.5.audit.v1\",\n          \"source\": {\n            \"build_id\": \"20251110T081149Z-d1fb623\",\n            \"commit\": \"d1fb623\",\n            \"sequence\": 0,\n            \"workspace\": \".\"\n          }\n        },\n        \"metadata\": {\n          \"audit.build_id\": \"20251110T081149Z-d1fb623\",\n          \"audit.channel\": \"cli\",\n          \"audit.policy.version\": \"phase2.5.audit.v1\",\n          \"audit.sequence\": 0,\n          \"audit.source.commit\": \"d1fb623\",\n          \"audit.source.workspace\": \".\",\n          \"audit.timestamp\": \"2025-11-10T08:11:49Z\",\n          \"cli.audit_id\": \"cli/20251110T081149Z-d1fb623#0\",\n          \"cli.change_set\": {\n            \"items\": [\n              {\n                \"args\": [\n                  \"/Users/dolphilia/github/kestrel/compiler/ocaml/_build/install/default/bin/remlc\",\n                  \"--packrat\",\n                  \"--format\",\n                  \"json\",\n                  \"--json-mode\",\n                  \"compact\",\n                  \"--emit-parse-debug\",\n                  \"/Users/dolphilia/github/kestrel/reports/dual-write/front-end/w4-diagnostics/20280418-w4-diag-effects-r3/stream_pending_resume/ocaml.parse-debug.json\",\n                  \"--left-recursion\",\n                  \"off\",\n                  \"--streaming\",\n                  \"--stream-resume-hint\",\n                  \"diag-w4\",\n                  \"--stream-flow-policy\",\n                  \"auto\",\n                  \"--stream-demand-min-bytes\",\n                  \"4\",\n                  \"--stream-demand-preferred-bytes\",\n                  \"8\",\n                  \"--stream-flow-max-lag\",\n                  \"8192\",\n                  \"/Users/dolphilia/github/kestrel/reports/dual-write/front-end/w4-diagnostics/20280418-w4-diag-effects-r3/stream_pending_resume/input.reml\"\n                ],\n                \"command\": \"remlc\",\n                \"kind\": \"cli-command\"\n              },\n              {\n                \"kind\": \"input\",\n                \"path\": \"input.reml\",\n                \"target\": \"x86_64-linux\"\n              },\n              {\n                \"kind\": \"outputs\",\n                \"values\": [\n                  \"emit_parse_debug\"\n                ]\n              }\n            ],\n            \"origin\": \"cli\",\n            \"policy\": \"phase2.5.audit.v1\",\n            \"source\": {\n              \"build_id\": \"20251110T081149Z-d1fb623\",\n              \"commit\": \"d1fb623\",\n              \"sequence\": 0,\n              \"workspace\": \".\"\n            }\n          },\n          \"effect.actual_capabilities\": [],\n          \"effect.capabilities\": [],\n          \"effect.required_capabilities\": [],\n          \"effect.stage.actual_capabilities\": [],\n          \"effect.stage.required_capabilities\": [],\n          \"event.domain\": \"parser\",\n          \"fingerprint\": \"859967339\",\n          \"name\": \"compilation_unit\",\n          \"namespace\": \"menhir\",\n          \"origin\": \"static\",\n          \"parser\": {\n            \"core\": {\n              \"rule\": {\n                \"fingerprint\": \"859967339\",\n                \"name\": \"compilation_unit\",\n                \"namespace\": \"menhir\",\n                \"ordinal\": 0,\n                \"origin\": \"static\"\n              }\n            }\n          },\n          \"parser.core.rule\": {\n            \"fingerprint\": \"859967339\",\n            \"name\": \"compilation_unit\",\n            \"namespace\": \"menhir\",\n            \"ordinal\": 0,\n            \"origin\": \"static\"\n          },\n          \"parser.core.rule.fingerprint\": \"859967339\",\n          \"parser.core.rule.name\": \"compilation_unit\",\n          \"parser.core.rule.namespace\": \"menhir\",\n          \"parser.core.rule.ordinal\": 0,\n          \"parser.core.rule.origin\": \"static\",\n          \"parser.runconfig\": {\n            \"experimental_effects\": false,\n            \"extensions\": {\n              \"lex\": {\n                \"identifier_profile\": \"unicode\",\n                \"profile\": \"strict_json\"\n              },\n              \"recover\": {\n                \"notes\": false,\n                \"sync_tokens\": []\n              },\n              \"stream\": {\n                \"checkpoint\": \"unspecified\",\n                \"chunk_size\": 0,\n                \"demand_min_bytes\": 4,\n                \"demand_preferred_bytes\": 8,\n                \"enabled\": true,\n                \"flow\": {\n                  \"backpressure\": {\n                    \"max_lag_bytes\": 8192\n                  },\n                  \"policy\": \"auto\"\n                },\n                \"resume_hint\": \"diag-w4\"\n              }\n            },\n            \"left_recursion\": \"off\",\n            \"legacy_result\": true,\n            \"merge_warnings\": true,\n            \"packrat\": true,\n            \"require_eof\": false,\n            \"trace\": false\n          },\n          \"parser.runconfig.experimental_effects\": false,\n          \"parser.runconfig.extensions.lex\": {\n            \"identifier_profile\": \"unicode\",\n            \"profile\": \"strict_json\"\n          },\n          \"parser.runconfig.extensions.lex.identifier_profile\": \"unicode\",\n          \"parser.runconfig.extensions.lex.profile\": \"strict_json\",\n          \"parser.runconfig.extensions.recover\": {\n            \"notes\": false,\n            \"sync_tokens\": []\n          },\n          \"parser.runconfig.extensions.recover.notes\": false,\n          \"parser.runconfig.extensions.recover.sync_tokens\": [],\n          \"parser.runconfig.extensions.stream\": {\n            \"checkpoint\": \"unspecified\",\n            \"chunk_size\": 0,\n            \"demand_min_bytes\": 4,\n            \"demand_preferred_bytes\": 8,\n            \"enabled\": true,\n            \"flow\": {\n              \"backpressure\": {\n                \"max_lag_bytes\": 8192\n              },\n              \"policy\": \"auto\"\n            },\n            \"resume_hint\": \"diag-w4\"\n          },\n          \"parser.runconfig.extensions.stream.checkpoint\": \"unspecified\",\n          \"parser.runconfig.extensions.stream.chunk_size\": 0,\n          \"parser.runconfig.extensions.stream.demand_min_bytes\": 4,\n          \"parser.runconfig.extensions.stream.demand_preferred_bytes\": 8,\n          \"parser.runconfig.extensions.stream.enabled\": true,\n          \"parser.runconfig.extensions.stream.flow.backpressure.max_lag_bytes\": 8192,\n          \"parser.runconfig.extensions.stream.flow.policy\": \"auto\",\n          \"parser.runconfig.extensions.stream.resume_hint\": \"diag-w4\",\n          \"parser.runconfig.left_recursion\": \"off\",\n          \"parser.runconfig.legacy_result\": true,\n          \"parser.runconfig.merge_warnings\": true,\n          \"parser.runconfig.packrat\": true,\n          \"parser.runconfig.require_eof\": false,\n          \"parser.runconfig.trace\": false,\n          \"schema.version\": \"1.1\"\n        }\n      },\n      \"audit_metadata\": {\n        \"audit.build_id\": \"20251110T081149Z-d1fb623\",\n        \"audit.channel\": \"cli\",\n        \"audit.policy.version\": \"phase2.5.audit.v1\",\n        \"audit.sequence\": 0,\n        \"audit.source.commit\": \"d1fb623\",\n        \"audit.source.workspace\": \".\",\n        \"audit.timestamp\": \"2025-11-10T08:11:49Z\",\n        \"cli.audit_id\": \"cli/20251110T081149Z-d1fb623#0\",\n        \"cli.change_set\": {\n          \"items\": [\n            {\n              \"args\": [\n                \"/Users/dolphilia/github/kestrel/compiler/ocaml/_build/install/default/bin/remlc\",\n                \"--packrat\",\n                \"--format\",\n                \"json\",\n                \"--json-mode\",\n                \"compact\",\n                \"--emit-parse-debug\",\n                \"/Users/dolphilia/github/kestrel/reports/dual-write/front-end/w4-diagnostics/20280418-w4-diag-effects-r3/stream_pending_resume/ocaml.parse-debug.json\",\n                \"--left-recursion\",\n                \"off\",\n                \"--streaming\",\n                \"--stream-resume-hint\",\n                \"diag-w4\",\n                \"--stream-flow-policy\",\n                \"auto\",\n                \"--stream-demand-min-bytes\",\n                \"4\",\n                \"--stream-demand-preferred-bytes\",\n                \"8\",\n                \"--stream-flow-max-lag\",\n                \"8192\",\n                \"/Users/dolphilia/github/kestrel/reports/dual-write/front-end/w4-diagnostics/20280418-w4-diag-effects-r3/stream_pending_resume/input.reml\"\n              ],\n              \"command\": \"remlc\",\n              \"kind\": \"cli-command\"\n            },\n            {\n              \"kind\": \"input\",\n              \"path\": \"input.reml\",\n              \"target\": \"x86_64-linux\"\n            },\n            {\n              \"kind\": \"outputs\",\n              \"values\": [\n                \"emit_parse_debug\"\n              ]\n            }\n          ],\n          \"origin\": \"cli\",\n          \"policy\": \"phase2.5.audit.v1\",\n          \"source\": {\n            \"build_id\": \"20251110T081149Z-d1fb623\",\n            \"commit\": \"d1fb623\",\n            \"sequence\": 0,\n            \"workspace\": \".\"\n          }\n        },\n        \"effect.actual_capabilities\": [],\n        \"effect.capabilities\": [],\n        \"effect.required_capabilities\": [],\n        \"effect.stage.actual_capabilities\": [],\n        \"effect.stage.required_capabilities\": [],\n        \"event.domain\": \"parser\",\n        \"fingerprint\": \"859967339\",\n        \"name\": \"compilation_unit\",\n        \"namespace\": \"menhir\",\n        \"origin\": \"static\",\n        \"parser\": {\n          \"core\": {\n            \"rule\": {\n              \"fingerprint\": \"859967339\",\n              \"name\": \"compilation_unit\",\n              \"namespace\": \"menhir\",\n              \"ordinal\": 0,\n              \"origin\": \"static\"\n            }\n          }\n        },\n        \"parser.core.rule\": {\n          \"fingerprint\": \"859967339\",\n          \"name\": \"compilation_unit\",\n          \"namespace\": \"menhir\",\n          \"ordinal\": 0,\n          \"origin\": \"static\"\n        },\n        \"parser.core.rule.fingerprint\": \"859967339\",\n        \"parser.core.rule.name\": \"compilation_unit\",\n        \"parser.core.rule.namespace\": \"menhir\",\n        \"parser.core.rule.ordinal\": 0,\n        \"parser.core.rule.origin\": \"static\",\n        \"parser.runconfig\": {\n          \"experimental_effects\": false,\n          \"extensions\": {\n            \"lex\": {\n              \"identifier_profile\": \"unicode\",\n              \"profile\": \"strict_json\"\n            },\n            \"recover\": {\n              \"notes\": false,\n              \"sync_tokens\": []\n            },\n            \"stream\": {\n              \"checkpoint\": \"unspecified\",\n              \"chunk_size\": 0,\n              \"demand_min_bytes\": 4,\n              \"demand_preferred_bytes\": 8,\n              \"enabled\": true,\n              \"flow\": {\n                \"backpressure\": {\n                  \"max_lag_bytes\": 8192\n                },\n                \"policy\": \"auto\"\n              },\n              \"resume_hint\": \"diag-w4\"\n            }\n          },\n          \"left_recursion\": \"off\",\n          \"legacy_result\": true,\n          \"merge_warnings\": true,\n          \"packrat\": true,\n          \"require_eof\": false,\n          \"trace\": false\n        },\n        \"parser.runconfig.experimental_effects\": false,\n        \"parser.runconfig.extensions.lex\": {\n          \"identifier_profile\": \"unicode\",\n          \"profile\": \"strict_json\"\n        },\n        \"parser.runconfig.extensions.lex.identifier_profile\": \"unicode\",\n        \"parser.runconfig.extensions.lex.profile\": \"strict_json\",\n        \"parser.runconfig.extensions.recover\": {\n          \"notes\": false,\n          \"sync_tokens\": []\n        },\n        \"parser.runconfig.extensions.recover.notes\": false,\n        \"parser.runconfig.extensions.recover.sync_tokens\": [],\n        \"parser.runconfig.extensions.stream\": {\n          \"checkpoint\": \"unspecified\",\n          \"chunk_size\": 0,\n          \"demand_min_bytes\": 4,\n          \"demand_preferred_bytes\": 8,\n          \"enabled\": true,\n          \"flow\": {\n            \"backpressure\": {\n              \"max_lag_bytes\": 8192\n            },\n            \"policy\": \"auto\"\n          },\n          \"resume_hint\": \"diag-w4\"\n        },\n        \"parser.runconfig.extensions.stream.checkpoint\": \"unspecified\",\n        \"parser.runconfig.extensions.stream.chunk_size\": 0,\n        \"parser.runconfig.extensions.stream.demand_min_bytes\": 4,\n        \"parser.runconfig.extensions.stream.demand_preferred_bytes\": 8,\n        \"parser.runconfig.extensions.stream.enabled\": true,\n        \"parser.runconfig.extensions.stream.flow.backpressure.max_lag_bytes\": 8192,\n        \"parser.runconfig.extensions.stream.flow.policy\": \"auto\",\n        \"parser.runconfig.extensions.stream.resume_hint\": \"diag-w4\",\n        \"parser.runconfig.left_recursion\": \"off\",\n        \"parser.runconfig.legacy_result\": true,\n        \"parser.runconfig.merge_warnings\": true,\n        \"parser.runconfig.packrat\": true,\n        \"parser.runconfig.require_eof\": false,\n        \"parser.runconfig.trace\": false,\n        \"schema.version\": \"1.1\"\n      },\n      \"domain\": \"parser\",\n      \"expected\": {\n        \"alternatives\": [\n          {\n            \"kind\": \"keyword\",\n            \"value\": \"continue\"\n          },\n          {\n            \"kind\": \"keyword\",\n            \"value\": \"defer\"\n          },\n          {\n            \"kind\": \"keyword\",\n            \"value\": \"do\"\n          },\n          {\n            \"kind\": \"keyword\",\n            \"value\": \"false\"\n          },\n          {\n            \"kind\": \"keyword\",\n            \"value\": \"for\"\n          },\n          {\n            \"kind\": \"keyword\",\n            \"value\": \"handle\"\n          },\n          {\n            \"kind\": \"keyword\",\n            \"value\": \"if\"\n          },\n          {\n            \"kind\": \"keyword\",\n            \"value\": \"loop\"\n          },\n          {\n            \"kind\": \"keyword\",\n            \"value\": \"match\"\n          },\n          {\n            \"kind\": \"keyword\",\n            \"value\": \"perform\"\n          },\n          {\n            \"kind\": \"keyword\",\n            \"value\": \"return\"\n          },\n          {\n            \"kind\": \"keyword\",\n            \"value\": \"self\"\n          },\n          {\n            \"kind\": \"keyword\",\n            \"value\": \"true\"\n          },\n          {\n            \"kind\": \"keyword\",\n            \"value\": \"unsafe\"\n          },\n          {\n            \"kind\": \"keyword\",\n            \"value\": \"while\"\n          },\n          {\n            \"kind\": \"token\",\n            \"value\": \"!\"\n          },\n          {\n            \"kind\": \"token\",\n            \"value\": \"(\"\n          },\n          {\n            \"kind\": \"token\",\n            \"value\": \"-\"\n          },\n          {\n            \"kind\": \"token\",\n            \"value\": \"[\"\n          },\n          {\n            \"kind\": \"token\",\n            \"value\": \"{\"\n          },\n          {\n            \"kind\": \"token\",\n            \"value\": \"|\"\n          },\n          {\n            \"kind\": \"class\",\n            \"value\": \"char-literal\"\n          },\n          {\n            \"kind\": \"class\",\n            \"value\": \"float-literal\"\n          },\n          {\n            \"kind\": \"class\",\n            \"value\": \"identifier\"\n          },\n          {\n            \"kind\": \"class\",\n            \"value\": \"integer-literal\"\n          },\n          {\n            \"kind\": \"class\",\n            \"value\": \"string-literal\"\n          },\n          {\n            \"kind\": \"class\",\n            \"value\": \"upper-identifier\"\n          }\n        ],\n        \"humanized\": \"ここで`continue`、`defer`、`do`、`false`、`for`、`handle`、`if`、`loop`、`match`、`perform`、`return`、`self`、`true`、`unsafe`、`while`、`!`、`(`、`-`、`[`、`{`、`|`、char-literal、float-literal、identifier、integer-literal、string-literal または upper-identifierのいずれかが必要です\",\n        \"locale_args\": [\n          \"continue\",\n          \"defer\",\n          \"do\",\n          \"false\",\n          \"for\",\n          \"handle\",\n          \"if\",\n          \"loop\",\n          \"match\",\n          \"perform\",\n          \"return\",\n          \"self\",\n          \"true\",\n          \"unsafe\",\n          \"while\",\n          \"!\",\n          \"(\",\n          \"-\",\n          \"[\",\n          \"{\",\n          \"|\",\n          \"char-literal\",\n          \"float-literal\",\n          \"identifier\",\n          \"integer-literal\",\n          \"string-literal\",\n          \"upper-identifier\"\n        ],\n        \"message_key\": \"parse.expected\"\n      },\n      \"extensions\": {\n        \"diagnostic.v2\": {\n          \"timestamp\": \"2025-11-10T08:11:49Z\"\n        },\n        \"effect.actual_capabilities\": [],\n        \"effect.capabilities\": [],\n        \"effect.required_capabilities\": [],\n        \"effect.stage.actual_capabilities\": [],\n        \"effect.stage.required_capabilities\": [],\n        \"parse\": {\n          \"parser_id\": {\n            \"fingerprint\": \"859967339\",\n            \"name\": \"compilation_unit\",\n            \"namespace\": \"menhir\",\n            \"ordinal\": 0,\n            \"origin\": \"static\"\n          }\n        },\n        \"recover\": {\n          \"expected_tokens\": [\n            {\n              \"kind\": \"keyword\",\n              \"label\": \"continue\"\n            },\n            {\n              \"kind\": \"keyword\",\n              \"label\": \"defer\"\n            },\n            {\n              \"kind\": \"keyword\",\n              \"label\": \"do\"\n            },\n            {\n              \"kind\": \"keyword\",\n              \"label\": \"false\"\n            },\n            {\n              \"kind\": \"keyword\",\n              \"label\": \"for\"\n            },\n            {\n              \"kind\": \"keyword\",\n              \"label\": \"handle\"\n            },\n            {\n              \"kind\": \"keyword\",\n              \"label\": \"if\"\n            },\n            {\n              \"kind\": \"keyword\",\n              \"label\": \"loop\"\n            },\n            {\n              \"kind\": \"keyword\",\n              \"label\": \"match\"\n            },\n            {\n              \"kind\": \"keyword\",\n              \"label\": \"perform\"\n            },\n            {\n              \"kind\": \"keyword\",\n              \"label\": \"return\"\n            },\n            {\n              \"kind\": \"keyword\",\n              \"label\": \"self\"\n            },\n            {\n              \"kind\": \"keyword\",\n              \"label\": \"true\"\n            },\n            {\n              \"kind\": \"keyword\",\n              \"label\": \"unsafe\"\n            },\n            {\n              \"kind\": \"keyword\",\n              \"label\": \"while\"\n            },\n            {\n              \"kind\": \"token\",\n              \"label\": \"!\"\n            },\n            {\n              \"kind\": \"token\",\n              \"label\": \"(\"\n            },\n            {\n              \"kind\": \"token\",\n              \"label\": \"-\"\n            },\n            {\n              \"kind\": \"token\",\n              \"label\": \"[\"\n            },\n            {\n              \"kind\": \"token\",\n              \"label\": \"{\"\n            },\n            {\n              \"kind\": \"token\",\n              \"label\": \"|\"\n            },\n            {\n              \"kind\": \"class\",\n              \"label\": \"char-literal\"\n            },\n            {\n              \"kind\": \"class\",\n              \"label\": \"float-literal\"\n            },\n            {\n              \"kind\": \"class\",\n              \"label\": \"identifier\"\n            },\n            {\n              \"kind\": \"class\",\n              \"label\": \"integer-literal\"\n            },\n            {\n              \"kind\": \"class\",\n              \"label\": \"string-literal\"\n            },\n            {\n              \"kind\": \"class\",\n              \"label\": \"upper-identifier\"\n            }\n          ],\n          \"message\": \"ここで`continue`、`defer`、`do`、`false`、`for`、`handle`、`if`、`loop`、`match`、`perform`、`return`、`self`、`true`、`unsafe`、`while`、`!`、`(`、`-`、`[`、`{`、`|`、char-literal、float-literal、identifier、integer-literal、string-literal または upper-identifierのいずれかが必要です\"\n        },\n        \"runconfig\": {\n          \"experimental_effects\": false,\n          \"extensions\": {\n            \"lex\": {\n              \"identifier_profile\": \"unicode\",\n              \"profile\": \"strict_json\"\n            },\n            \"recover\": {\n              \"notes\": false,\n              \"sync_tokens\": []\n            },\n            \"stream\": {\n              \"checkpoint\": \"unspecified\",\n              \"chunk_size\": 0,\n              \"demand_min_bytes\": 4,\n              \"demand_preferred_bytes\": 8,\n              \"enabled\": true,\n              \"flow\": {\n                \"backpressure\": {\n                  \"max_lag_bytes\": 8192\n                },\n                \"policy\": \"auto\"\n              },\n              \"resume_hint\": \"diag-w4\"\n            }\n          },\n          \"left_recursion\": \"off\",\n          \"legacy_result\": true,\n          \"merge_warnings\": true,\n          \"packrat\": true,\n          \"require_eof\": false,\n          \"trace\": false\n        }\n      },\n      \"location\": {\n        \"column\": 15,\n        \"endColumn\": 16,\n        \"endLine\": 3,\n        \"file\": \"/Users/dolphilia/github/kestrel/reports/dual-write/front-end/w4-diagnostics/20280418-w4-diag-effects-r3/stream_pending_resume/input.reml\",\n        \"line\": 3\n      },\n      \"message\": \"Unexpected character: \\\\\",\n      \"schema_version\": \"2.0.0-draft\",\n      \"severity\": \"error\",\n      \"timestamp\": \"2025-11-10T08:11:49Z\"\n    }\n  ]\n}",
  "rust_sorted": "{\n  \"diagnostics\": [\n    {\n      \"audit\": {\n        \"audit_id\": \"cli/20251110T081149Z#0\",\n        \"change_set\": {\n          \"items\": [\n            {\n              \"args\": [\n                \"--emit-parse-debug\",\n                \"/Users/dolphilia/github/kestrel/reports/dual-write/front-end/w4-diagnostics/20280418-w4-diag-effects-r3/stream_pending_resume/rust.parse-debug.json\",\n                \"--dualwrite-root\",\n                \"/Users/dolphilia/github/kestrel/reports/dual-write/front-end/w4-diagnostics\",\n                \"--dualwrite-run-label\",\n                \"20280418-w4-diag-effects-r3\",\n                \"--dualwrite-case-label\",\n                \"stream_pending_resume\",\n                \"--streaming\",\n                \"--stream-resume-hint\",\n                \"diag-w4\",\n                \"--stream-flow-policy\",\n                \"auto\",\n                \"--stream-demand-min-bytes\",\n                \"4\",\n                \"--stream-demand-preferred-bytes\",\n                \"8\",\n                \"--stream-flow-max-lag\",\n                \"8192\",\n                \"/Users/dolphilia/github/kestrel/reports/dual-write/front-end/w4-diagnostics/20280418-w4-diag-effects-r3/stream_pending_resume/input.reml\"\n              ],\n              \"command\": \"target/debug/poc_frontend\",\n              \"kind\": \"cli-command\"\n            },\n            {\n              \"kind\": \"input\",\n              \"path\": \"/Users/dolphilia/github/kestrel/reports/dual-write/front-end/w4-diagnostics/20280418-w4-diag-effects-r3/stream_pending_resume/input.reml\",\n              \"target\": \"rust-poc\"\n            }\n          ],\n          \"origin\": \"cli\",\n          \"policy\": \"rust.poc.audit.v1\",\n          \"source\": {\n            \"args\": [\n              \"--emit-parse-debug\",\n              \"/Users/dolphilia/github/kestrel/reports/dual-write/front-end/w4-diagnostics/20280418-w4-diag-effects-r3/stream_pending_resume/rust.parse-debug.json\",\n              \"--dualwrite-root\",\n              \"/Users/dolphilia/github/kestrel/reports/dual-write/front-end/w4-diagnostics\",\n              \"--dualwrite-run-label\",\n              \"20280418-w4-diag-effects-r3\",\n              \"--dualwrite-case-label\",\n              \"stream_pending_resume\",\n              \"--streaming\",\n              \"--stream-resume-hint\",\n              \"diag-w4\",\n              \"--stream-flow-policy\",\n              \"auto\",\n              \"--stream-demand-min-bytes\",\n              \"4\",\n              \"--stream-demand-preferred-bytes\",\n              \"8\",\n              \"--stream-flow-max-lag\",\n              \"8192\",\n              \"/Users/dolphilia/github/kestrel/reports/dual-write/front-end/w4-diagnostics/20280418-w4-diag-effects-r3/stream_pending_resume/input.reml\"\n            ],\n            \"command\": \"target/debug/poc_frontend\",\n            \"workspace\": \".\"\n          }\n        },\n        \"metadata\": {\n          \"audit.channel\": \"cli\",\n          \"audit.policy.version\": \"rust.poc.audit.v1\",\n          \"audit.timestamp\": \"2025-11-10T08:11:49Z\",\n          \"bridge.stage.actual_capabilities\": [],\n          \"bridge.stage.required_capabilities\": [],\n          \"capability.ids\": [],\n          \"cli.audit_id\": \"cli/20251110T081149Z#0\",\n          \"cli.change_set\": {\n            \"items\": [\n              {\n                \"args\": [\n                  \"--emit-parse-debug\",\n                  \"/Users/dolphilia/github/kestrel/reports/dual-write/front-end/w4-diagnostics/20280418-w4-diag-effects-r3/stream_pending_resume/rust.parse-debug.json\",\n                  \"--dualwrite-root\",\n                  \"/Users/dolphilia/github/kestrel/reports/dual-write/front-end/w4-diagnostics\",\n                  \"--dualwrite-run-label\",\n                  \"20280418-w4-diag-effects-r3\",\n                  \"--dualwrite-case-label\",\n                  \"stream_pending_resume\",\n                  \"--streaming\",\n                  \"--stream-resume-hint\",\n                  \"diag-w4\",\n                  \"--stream-flow-policy\",\n                  \"auto\",\n                  \"--stream-demand-min-bytes\",\n                  \"4\",\n                  \"--stream-demand-preferred-bytes\",\n                  \"8\",\n                  \"--stream-flow-max-lag\",\n                  \"8192\",\n                  \"/Users/dolphilia/github/kestrel/reports/dual-write/front-end/w4-diagnostics/20280418-w4-diag-effects-r3/stream_pending_resume/input.reml\"\n                ],\n                \"command\": \"target/debug/poc_frontend\",\n                \"kind\": \"cli-command\"\n              },\n              {\n                \"kind\": \"input\",\n                \"path\": \"/Users/dolphilia/github/kestrel/reports/dual-write/front-end/w4-diagnostics/20280418-w4-diag-effects-r3/stream_pending_resume/input.reml\",\n                \"target\": \"rust-poc\"\n              }\n            ],\n            \"origin\": \"cli\",\n            \"policy\": \"rust.poc.audit.v1\",\n            \"source\": {\n              \"args\": [\n                \"--emit-parse-debug\",\n                \"/Users/dolphilia/github/kestrel/reports/dual-write/front-end/w4-diagnostics/20280418-w4-diag-effects-r3/stream_pending_resume/rust.parse-debug.json\",\n                \"--dualwrite-root\",\n                \"/Users/dolphilia/github/kestrel/reports/dual-write/front-end/w4-diagnostics\",\n                \"--dualwrite-run-label\",\n                \"20280418-w4-diag-effects-r3\",\n                \"--dualwrite-case-label\",\n                \"stream_pending_resume\",\n                \"--streaming\",\n                \"--stream-resume-hint\",\n                \"diag-w4\",\n                \"--stream-flow-policy\",\n                \"auto\",\n                \"--stream-demand-min-bytes\",\n                \"4\",\n                \"--stream-demand-preferred-bytes\",\n                \"8\",\n                \"--stream-flow-max-lag\",\n                \"8192\",\n                \"/Users/dolphilia/github/kestrel/reports/dual-write/front-end/w4-diagnostics/20280418-w4-diag-effects-r3/stream_pending_resume/input.reml\"\n              ],\n              \"command\": \"target/debug/poc_frontend\",\n              \"workspace\": \".\"\n            }\n          },\n          \"effect.actual_capabilities\": [],\n          \"effect.required_capabilities\": [],\n          \"effect.stage.actual\": \"at_least:stable\",\n          \"effect.stage.actual_capabilities\": [],\n          \"effect.stage.required\": \"at_least:beta\",\n          \"effect.stage.required_capabilities\": [],\n          \"effect.stage.trace\": [\n            {\n              \"note\": \"--effect-stage\",\n              \"source\": \"cli_option\",\n              \"stage\": \"at_least:beta\"\n            },\n            {\n              \"source\": \"runtime\",\n              \"stage\": \"at_least:stable\"\n            }\n          ],\n          \"event.domain\": \"parser\",\n          \"event.kind\": \"diagnostic\",\n          \"fingerprint\": \"rust-poc-0001\",\n          \"name\": \"compilation_unit\",\n          \"namespace\": \"rust.poc\",\n          \"origin\": \"poc_frontend\",\n          \"parser.core.rule.fingerprint\": \"rust-poc-0001\",\n          \"parser.core.rule.name\": \"compilation_unit\",\n          \"parser.core.rule.namespace\": \"rust.poc\",\n          \"parser.core.rule.ordinal\": 0,\n          \"parser.core.rule.origin\": \"poc_frontend\",\n          \"parser.runconfig\": {\n            \"extensions\": {\n              \"config\": {\n                \"path\": null\n              },\n              \"effects\": {\n                \"type_row_mode\": \"ty-integrated\"\n              },\n              \"lex\": {\n                \"identifier_profile\": \"unicode\",\n                \"profile\": \"strict_json\"\n              },\n              \"recover\": {\n                \"notes\": false,\n                \"sync_tokens\": []\n              },\n              \"stream\": {\n                \"checkpoint\": \"unspecified\",\n                \"chunk_size\": 0,\n                \"demand_min_bytes\": 4,\n                \"demand_preferred_bytes\": 8,\n                \"enabled\": true,\n                \"flow\": {\n                  \"backpressure\": {\n                    \"max_lag_bytes\": 8192\n                  },\n                  \"policy\": \"auto\"\n                },\n                \"flow_max_lag\": 8192,\n                \"flow_policy\": \"auto\",\n                \"resume_hint\": \"diag-w4\"\n              }\n            },\n            \"runtime_capabilities\": [],\n            \"switches\": {\n              \"experimental_effects\": false,\n              \"left_recursion\": \"off\",\n              \"legacy_result\": true,\n              \"merge_warnings\": true,\n              \"packrat\": true,\n              \"require_eof\": false,\n              \"trace\": false\n            }\n          },\n          \"parser.runconfig.extensions.lex\": {\n            \"identifier_profile\": \"unicode\",\n            \"profile\": \"strict_json\"\n          },\n          \"parser.runconfig.extensions.lex.identifier_profile\": \"unicode\",\n          \"parser.runconfig.extensions.lex.profile\": \"strict_json\",\n          \"parser.runconfig.extensions.recover\": {\n            \"notes\": false,\n            \"sync_tokens\": []\n          },\n          \"parser.runconfig.extensions.recover.notes\": false,\n          \"parser.runconfig.extensions.recover.sync_tokens\": [],\n          \"parser.runconfig.extensions.stream\": {\n            \"checkpoint\": \"unspecified\",\n            \"chunk_size\": 0,\n            \"demand_min_bytes\": 4,\n            \"demand_preferred_bytes\": 8,\n            \"enabled\": true,\n            \"flow\": {\n              \"backpressure\": {\n                \"max_lag_bytes\": 8192\n              },\n              \"policy\": \"auto\"\n            },\n            \"flow_max_lag\": 8192,\n            \"flow_policy\": \"auto\",\n            \"resume_hint\": \"diag-w4\"\n          },\n          \"parser.runconfig.extensions.stream.checkpoint\": \"unspecified\",\n          \"parser.runconfig.extensions.stream.chunk_size\": 0,\n          \"parser.runconfig.extensions.stream.demand_min_bytes\": 4,\n          \"parser.runconfig.extensions.stream.demand_preferred_bytes\": 8,\n          \"parser.runconfig.extensions.stream.enabled\": true,\n          \"parser.runconfig.extensions.stream.flow.backpressure.max_lag_bytes\": 8192,\n          \"parser.runconfig.extensions.stream.flow.policy\": \"auto\",\n          \"parser.runconfig.extensions.stream.resume_hint\": \"diag-w4\",\n          \"parser.runconfig.switches.left_recursion\": \"off\",\n          \"parser.runconfig.switches.legacy_result\": true,\n          \"parser.runconfig.switches.merge_warnings\": true,\n          \"parser.runconfig.switches.packrat\": true,\n          \"parser.runconfig.switches.require_eof\": false,\n          \"parser.runconfig.switches.trace\": false,\n          \"parser.stream.checkpoint\": \"unspecified\",\n          \"parser.stream.demand_min_bytes\": 4,\n          \"parser.stream.demand_preferred_bytes\": 8,\n          \"parser.stream.flow_max_lag\": 8192,\n          \"parser.stream.flow_policy\": \"auto\",\n          \"parser.stream.resume_hint\": \"diag-w4\",\n          \"schema.version\": \"2.0.0-draft\",\n          \"stage.trace\": [\n            {\n              \"note\": \"--effect-stage\",\n              \"source\": \"cli_option\",\n              \"stage\": \"at_least:beta\"\n            },\n            {\n              \"source\": \"runtime\",\n              \"stage\": \"at_least:stable\"\n            }\n          ]\n        }\n      },\n      \"audit_metadata\": {\n        \"audit.channel\": \"cli\",\n        \"audit.policy.version\": \"rust.poc.audit.v1\",\n        \"audit.timestamp\": \"2025-11-10T08:11:49Z\",\n        \"bridge.stage.actual_capabilities\": [],\n        \"bridge.stage.required_capabilities\": [],\n        \"capability.ids\": [],\n        \"cli.audit_id\": \"cli/20251110T081149Z#0\",\n        \"cli.change_set\": {\n          \"items\": [\n            {\n              \"args\": [\n                \"--emit-parse-debug\",\n                \"/Users/dolphilia/github/kestrel/reports/dual-write/front-end/w4-diagnostics/20280418-w4-diag-effects-r3/stream_pending_resume/rust.parse-debug.json\",\n                \"--dualwrite-root\",\n                \"/Users/dolphilia/github/kestrel/reports/dual-write/front-end/w4-diagnostics\",\n                \"--dualwrite-run-label\",\n                \"20280418-w4-diag-effects-r3\",\n                \"--dualwrite-case-label\",\n                \"stream_pending_resume\",\n                \"--streaming\",\n                \"--stream-resume-hint\",\n                \"diag-w4\",\n                \"--stream-flow-policy\",\n                \"auto\",\n                \"--stream-demand-min-bytes\",\n                \"4\",\n                \"--stream-demand-preferred-bytes\",\n                \"8\",\n                \"--stream-flow-max-lag\",\n                \"8192\",\n                \"/Users/dolphilia/github/kestrel/reports/dual-write/front-end/w4-diagnostics/20280418-w4-diag-effects-r3/stream_pending_resume/input.reml\"\n              ],\n              \"command\": \"target/debug/poc_frontend\",\n              \"kind\": \"cli-command\"\n            },\n            {\n              \"kind\": \"input\",\n              \"path\": \"/Users/dolphilia/github/kestrel/reports/dual-write/front-end/w4-diagnostics/20280418-w4-diag-effects-r3/stream_pending_resume/input.reml\",\n              \"target\": \"rust-poc\"\n            }\n          ],\n          \"origin\": \"cli\",\n          \"policy\": \"rust.poc.audit.v1\",\n          \"source\": {\n            \"args\": [\n              \"--emit-parse-debug\",\n              \"/Users/dolphilia/github/kestrel/reports/dual-write/front-end/w4-diagnostics/20280418-w4-diag-effects-r3/stream_pending_resume/rust.parse-debug.json\",\n              \"--dualwrite-root\",\n              \"/Users/dolphilia/github/kestrel/reports/dual-write/front-end/w4-diagnostics\",\n              \"--dualwrite-run-label\",\n              \"20280418-w4-diag-effects-r3\",\n              \"--dualwrite-case-label\",\n              \"stream_pending_resume\",\n              \"--streaming\",\n              \"--stream-resume-hint\",\n              \"diag-w4\",\n              \"--stream-flow-policy\",\n              \"auto\",\n              \"--stream-demand-min-bytes\",\n              \"4\",\n              \"--stream-demand-preferred-bytes\",\n              \"8\",\n              \"--stream-flow-max-lag\",\n              \"8192\",\n              \"/Users/dolphilia/github/kestrel/reports/dual-write/front-end/w4-diagnostics/20280418-w4-diag-effects-r3/stream_pending_resume/input.reml\"\n            ],\n            \"command\": \"target/debug/poc_frontend\",\n            \"workspace\": \".\"\n          }\n        },\n        \"effect.actual_capabilities\": [],\n        \"effect.required_capabilities\": [],\n        \"effect.stage.actual\": \"at_least:stable\",\n        \"effect.stage.actual_capabilities\": [],\n        \"effect.stage.required\": \"at_least:beta\",\n        \"effect.stage.required_capabilities\": [],\n        \"effect.stage.trace\": [\n          {\n            \"note\": \"--effect-stage\",\n            \"source\": \"cli_option\",\n            \"stage\": \"at_least:beta\"\n          },\n          {\n            \"source\": \"runtime\",\n            \"stage\": \"at_least:stable\"\n          }\n        ],\n        \"event.domain\": \"parser\",\n        \"event.kind\": \"diagnostic\",\n        \"fingerprint\": \"rust-poc-0001\",\n        \"name\": \"compilation_unit\",\n        \"namespace\": \"rust.poc\",\n        \"origin\": \"poc_frontend\",\n        \"parser.core.rule.fingerprint\": \"rust-poc-0001\",\n        \"parser.core.rule.name\": \"compilation_unit\",\n        \"parser.core.rule.namespace\": \"rust.poc\",\n        \"parser.core.rule.ordinal\": 0,\n        \"parser.core.rule.origin\": \"poc_frontend\",\n        \"parser.runconfig\": {\n          \"extensions\": {\n            \"config\": {\n              \"path\": null\n            },\n            \"effects\": {\n              \"type_row_mode\": \"ty-integrated\"\n            },\n            \"lex\": {\n              \"identifier_profile\": \"unicode\",\n              \"profile\": \"strict_json\"\n            },\n            \"recover\": {\n              \"notes\": false,\n              \"sync_tokens\": []\n            },\n            \"stream\": {\n              \"checkpoint\": \"unspecified\",\n              \"chunk_size\": 0,\n              \"demand_min_bytes\": 4,\n              \"demand_preferred_bytes\": 8,\n              \"enabled\": true,\n              \"flow\": {\n                \"backpressure\": {\n                  \"max_lag_bytes\": 8192\n                },\n                \"policy\": \"auto\"\n              },\n              \"flow_max_lag\": 8192,\n              \"flow_policy\": \"auto\",\n              \"resume_hint\": \"diag-w4\"\n            }\n          },\n          \"runtime_capabilities\": [],\n          \"switches\": {\n            \"experimental_effects\": false,\n            \"left_recursion\": \"off\",\n            \"legacy_result\": true,\n            \"merge_warnings\": true,\n            \"packrat\": true,\n            \"require_eof\": false,\n            \"trace\": false\n          }\n        },\n        \"parser.runconfig.extensions.lex\": {\n          \"identifier_profile\": \"unicode\",\n          \"profile\": \"strict_json\"\n        },\n        \"parser.runconfig.extensions.lex.identifier_profile\": \"unicode\",\n        \"parser.runconfig.extensions.lex.profile\": \"strict_json\",\n        \"parser.runconfig.extensions.recover\": {\n          \"notes\": false,\n          \"sync_tokens\": []\n        },\n        \"parser.runconfig.extensions.recover.notes\": false,\n        \"parser.runconfig.extensions.recover.sync_tokens\": [],\n        \"parser.runconfig.extensions.stream\": {\n          \"checkpoint\": \"unspecified\",\n          \"chunk_size\": 0,\n          \"demand_min_bytes\": 4,\n          \"demand_preferred_bytes\": 8,\n          \"enabled\": true,\n          \"flow\": {\n            \"backpressure\": {\n              \"max_lag_bytes\": 8192\n            },\n            \"policy\": \"auto\"\n          },\n          \"flow_max_lag\": 8192,\n          \"flow_policy\": \"auto\",\n          \"resume_hint\": \"diag-w4\"\n        },\n        \"parser.runconfig.extensions.stream.checkpoint\": \"unspecified\",\n        \"parser.runconfig.extensions.stream.chunk_size\": 0,\n        \"parser.runconfig.extensions.stream.demand_min_bytes\": 4,\n        \"parser.runconfig.extensions.stream.demand_preferred_bytes\": 8,\n        \"parser.runconfig.extensions.stream.enabled\": true,\n        \"parser.runconfig.extensions.stream.flow.backpressure.max_lag_bytes\": 8192,\n        \"parser.runconfig.extensions.stream.flow.policy\": \"auto\",\n        \"parser.runconfig.extensions.stream.resume_hint\": \"diag-w4\",\n        \"parser.runconfig.switches.left_recursion\": \"off\",\n        \"parser.runconfig.switches.legacy_result\": true,\n        \"parser.runconfig.switches.merge_warnings\": true,\n        \"parser.runconfig.switches.packrat\": true,\n        \"parser.runconfig.switches.require_eof\": false,\n        \"parser.runconfig.switches.trace\": false,\n        \"parser.stream.checkpoint\": \"unspecified\",\n        \"parser.stream.demand_min_bytes\": 4,\n        \"parser.stream.demand_preferred_bytes\": 8,\n        \"parser.stream.flow_max_lag\": 8192,\n        \"parser.stream.flow_policy\": \"auto\",\n        \"parser.stream.resume_hint\": \"diag-w4\",\n        \"schema.version\": \"2.0.0-draft\",\n        \"stage.trace\": [\n          {\n            \"note\": \"--effect-stage\",\n            \"source\": \"cli_option\",\n            \"stage\": \"at_least:beta\"\n          },\n          {\n            \"source\": \"runtime\",\n            \"stage\": \"at_least:stable\"\n          }\n        ]\n      },\n      \"code\": null,\n      \"domain\": \"parser\",\n      \"expected\": {\n        \"alternatives\": [\n          {\n            \"kind\": \"keyword\",\n            \"label\": \"fn\"\n          }\n        ],\n        \"humanized\": \"ここで`fn`が必要です\",\n        \"locale_args\": [\n          \"fn\"\n        ],\n        \"message_key\": \"parse.expected\"\n      },\n      \"extensions\": {\n        \"capability\": {\n          \"detail\": [],\n          \"ids\": [],\n          \"required_capabilities\": [],\n          \"stage\": {\n            \"actual\": \"at_least:stable\",\n            \"required\": \"at_least:beta\"\n          }\n        },\n        \"diagnostic.v2\": {\n          \"timestamp\": \"2025-11-10T08:11:49Z\"\n        },\n        \"effect.actual_capabilities\": [],\n        \"effect.capabilities\": [],\n        \"effect.required_capabilities\": [],\n        \"effect.stage.actual\": \"at_least:stable\",\n        \"effect.stage.actual_capabilities\": [],\n        \"effect.stage.required\": \"at_least:beta\",\n        \"effect.stage.required_capabilities\": [],\n        \"parse\": {\n          \"parser_id\": {\n            \"fingerprint\": \"rust-poc-0001\",\n            \"name\": \"compilation_unit\",\n            \"namespace\": \"rust.poc\",\n            \"ordinal\": 0,\n            \"origin\": \"poc_frontend\"\n          }\n        },\n        \"recover\": {\n          \"expected_tokens\": [\n            {\n              \"kind\": \"keyword\",\n              \"label\": \"fn\"\n            }\n          ],\n          \"message\": \"ここで`fn`が必要です\"\n        },\n        \"runconfig\": {\n          \"experimental_effects\": false,\n          \"extensions\": {\n            \"lex\": {\n              \"identifier_profile\": \"unicode\",\n              \"profile\": \"strict_json\"\n            },\n            \"recover\": {\n              \"notes\": false,\n              \"sync_tokens\": []\n            },\n            \"stream\": {\n              \"checkpoint\": \"unspecified\",\n              \"chunk_size\": 0,\n              \"demand_min_bytes\": 4,\n              \"demand_preferred_bytes\": 8,\n              \"enabled\": true,\n              \"flow\": {\n                \"backpressure\": {\n                  \"max_lag_bytes\": 8192\n                },\n                \"policy\": \"auto\"\n              },\n              \"flow_max_lag\": 8192,\n              \"flow_policy\": \"auto\",\n              \"resume_hint\": \"diag-w4\"\n            }\n          },\n          \"left_recursion\": \"off\",\n          \"legacy_result\": true,\n          \"merge_warnings\": true,\n          \"packrat\": true,\n          \"require_eof\": false,\n          \"trace\": false\n        }\n      },\n      \"location\": {\n        \"column\": 1,\n        \"endColumn\": 7,\n        \"endLine\": 1,\n        \"file\": \"/Users/dolphilia/github/kestrel/reports/dual-write/front-end/w4-diagnostics/20280418-w4-diag-effects-r3/stream_pending_resume/input.reml\",\n        \"line\": 1\n      },\n      \"message\": \"構文エラー: 入力を解釈できません\",\n      \"notes\": [\n        {\n          \"label\": \"recover.expected_tokens\",\n          \"message\": \"ここで`fn`が必要です\",\n          \"span\": null\n        }\n      ],\n      \"recoverability\": \"recoverable\",\n      \"schema_version\": \"2.0.0-draft\",\n      \"severity\": \"error\",\n      \"timestamp\": \"2025-11-10T08:11:49Z\"\n    }\n  ],\n  \"input\": \"/Users/dolphilia/github/kestrel/reports/dual-write/front-end/w4-diagnostics/20280418-w4-diag-effects-r3/stream_pending_resume/input.reml\",\n  \"parse_result\": {\n    \"packrat_stats\": {\n      \"approx_bytes\": 283,\n      \"budget_drops\": 0,\n      \"entries\": 1,\n      \"evictions\": 0,\n      \"hits\": 6,\n      \"pruned\": 0,\n      \"queries\": 7\n    },\n    \"span_trace\": [\n      {\n        \"label\": \"parser.simple_error\",\n        \"span\": {\n          \"end\": 6,\n          \"start\": 0\n        }\n      }\n    ]\n  },\n  \"run_config\": {\n    \"extensions\": {\n      \"config\": {\n        \"path\": null\n      },\n      \"effects\": {\n        \"type_row_mode\": \"ty-integrated\"\n      },\n      \"lex\": {\n        \"identifier_profile\": \"unicode\",\n        \"profile\": \"strict_json\"\n      },\n      \"recover\": {\n        \"notes\": false,\n        \"sync_tokens\": []\n      },\n      \"stream\": {\n        \"checkpoint\": \"unspecified\",\n        \"chunk_size\": 0,\n        \"demand_min_bytes\": 4,\n        \"demand_preferred_bytes\": 8,\n        \"enabled\": true,\n        \"flow\": {\n          \"backpressure\": {\n            \"max_lag_bytes\": 8192\n          },\n          \"policy\": \"auto\"\n        },\n        \"flow_max_lag\": 8192,\n        \"flow_policy\": \"auto\",\n        \"resume_hint\": \"diag-w4\"\n      }\n    },\n    \"runtime_capabilities\": [],\n    \"switches\": {\n      \"experimental_effects\": false,\n      \"left_recursion\": \"off\",\n      \"legacy_result\": true,\n      \"merge_warnings\": true,\n      \"packrat\": true,\n      \"require_eof\": false,\n      \"trace\": false\n    }\n  },\n  \"stream_meta\": {\n    \"packrat\": {\n      \"approx_bytes\": 283,\n      \"budget_drops\": 0,\n      \"entries\": 1,\n      \"evictions\": 0,\n      \"hits\": 6,\n      \"pruned\": 0,\n      \"queries\": 7\n    },\n    \"span_trace\": {\n      \"dropped\": 0,\n      \"retained\": 1\n    }\n  }\n}",
  "diff": [
    "--- ocaml",
    "+++ rust",
    "@@ -2,21 +2,19 @@",
    "   \"diagnostics\": [",
    "     {",
    "       \"audit\": {",
    "-        \"audit_id\": \"cli/20251110T081149Z-d1fb623#0\",",
    "+        \"audit_id\": \"cli/20251110T081149Z#0\",",
    "         \"change_set\": {",
    "           \"items\": [",
    "             {",
    "               \"args\": [",
    "-                \"/Users/dolphilia/github/kestrel/compiler/ocaml/_build/install/default/bin/remlc\",",
    "-                \"--packrat\",",
    "-                \"--format\",",
    "-                \"json\",",
    "-                \"--json-mode\",",
    "-                \"compact\",",
    "                 \"--emit-parse-debug\",",
    "-                \"/Users/dolphilia/github/kestrel/reports/dual-write/front-end/w4-diagnostics/20280418-w4-diag-effects-r3/stream_pending_resume/ocaml.parse-debug.json\",",
    "-                \"--left-recursion\",",
    "-                \"off\",",
    "+                \"/Users/dolphilia/github/kestrel/reports/dual-write/front-end/w4-diagnostics/20280418-w4-diag-effects-r3/stream_pending_resume/rust.parse-debug.json\",",
    "+                \"--dualwrite-root\",",
    "+                \"/Users/dolphilia/github/kestrel/reports/dual-write/front-end/w4-diagnostics\",",
    "+                \"--dualwrite-run-label\",",
    "+                \"20280418-w4-diag-effects-r3\",",
    "+                \"--dualwrite-case-label\",",
    "+                \"stream_pending_resume\",",
    "                 \"--streaming\",",
    "                 \"--stream-resume-hint\",",
    "                 \"diag-w4\",",
    "@@ -30,53 +28,64 @@",
    "                 \"8192\",",
    "                 \"/Users/dolphilia/github/kestrel/reports/dual-write/front-end/w4-diagnostics/20280418-w4-diag-effects-r3/stream_pending_resume/input.reml\"",
    "               ],",
    "-              \"command\": \"remlc\",",
    "+              \"command\": \"target/debug/poc_frontend\",",
    "               \"kind\": \"cli-command\"",
    "             },",
    "             {",
    "               \"kind\": \"input\",",
    "-              \"path\": \"input.reml\",",
    "-              \"target\": \"x86_64-linux\"",
    "-            },",
    "-            {",
    "-              \"kind\": \"outputs\",",
    "-              \"values\": [",
    "-                \"emit_parse_debug\"",
    "-              ]",
    "+              \"path\": \"/Users/dolphilia/github/kestrel/reports/dual-write/front-end/w4-diagnostics/20280418-w4-diag-effects-r3/stream_pending_resume/input.reml\",",
    "+              \"target\": \"rust-poc\"",
    "             }",
    "           ],",
    "           \"origin\": \"cli\",",
    "-          \"policy\": \"phase2.5.audit.v1\",",
    "+          \"policy\": \"rust.poc.audit.v1\",",
    "           \"source\": {",
    "-            \"build_id\": \"20251110T081149Z-d1fb623\",",
    "-            \"commit\": \"d1fb623\",",
    "-            \"sequence\": 0,",
    "+            \"args\": [",
    "+              \"--emit-parse-debug\",",
    "+              \"/Users/dolphilia/github/kestrel/reports/dual-write/front-end/w4-diagnostics/20280418-w4-diag-effects-r3/stream_pending_resume/rust.parse-debug.json\",",
    "+              \"--dualwrite-root\",",
    "+              \"/Users/dolphilia/github/kestrel/reports/dual-write/front-end/w4-diagnostics\",",
    "+              \"--dualwrite-run-label\",",
    "+              \"20280418-w4-diag-effects-r3\",",
    "+              \"--dualwrite-case-label\",",
    "+              \"stream_pending_resume\",",
    "+              \"--streaming\",",
    "+              \"--stream-resume-hint\",",
    "+              \"diag-w4\",",
    "+              \"--stream-flow-policy\",",
    "+              \"auto\",",
    "+              \"--stream-demand-min-bytes\",",
    "+              \"4\",",
    "+              \"--stream-demand-preferred-bytes\",",
    "+              \"8\",",
    "+              \"--stream-flow-max-lag\",",
    "+              \"8192\",",
    "+              \"/Users/dolphilia/github/kestrel/reports/dual-write/front-end/w4-diagnostics/20280418-w4-diag-effects-r3/stream_pending_resume/input.reml\"",
    "+            ],",
    "+            \"command\": \"target/debug/poc_frontend\",",
    "             \"workspace\": \".\"",
    "           }",
    "         },",
    "         \"metadata\": {",
    "-          \"audit.build_id\": \"20251110T081149Z-d1fb623\",",
    "           \"audit.channel\": \"cli\",",
    "-          \"audit.policy.version\": \"phase2.5.audit.v1\",",
    "-          \"audit.sequence\": 0,",
    "-          \"audit.source.commit\": \"d1fb623\",",
    "-          \"audit.source.workspace\": \".\",",
    "+          \"audit.policy.version\": \"rust.poc.audit.v1\",",
    "           \"audit.timestamp\": \"2025-11-10T08:11:49Z\",",
    "-          \"cli.audit_id\": \"cli/20251110T081149Z-d1fb623#0\",",
    "+          \"bridge.stage.actual_capabilities\": [],",
    "+          \"bridge.stage.required_capabilities\": [],",
    "+          \"capability.ids\": [],",
    "+          \"cli.audit_id\": \"cli/20251110T081149Z#0\",",
    "           \"cli.change_set\": {",
    "             \"items\": [",
    "               {",
    "                 \"args\": [",
    "-                  \"/Users/dolphilia/github/kestrel/compiler/ocaml/_build/install/default/bin/remlc\",",
    "-                  \"--packrat\",",
    "-                  \"--format\",",
    "-                  \"json\",",
    "-                  \"--json-mode\",",
    "-                  \"compact\",",
    "                   \"--emit-parse-debug\",",
    "-                  \"/Users/dolphilia/github/kestrel/reports/dual-write/front-end/w4-diagnostics/20280418-w4-diag-effects-r3/stream_pending_resume/ocaml.parse-debug.json\",",
    "-                  \"--left-recursion\",",
    "-                  \"off\",",
    "+                  \"/Users/dolphilia/github/kestrel/reports/dual-write/front-end/w4-diagnostics/20280418-w4-diag-effects-r3/stream_pending_resume/rust.parse-debug.json\",",
    "+                  \"--dualwrite-root\",",
    "+                  \"/Users/dolphilia/github/kestrel/reports/dual-write/front-end/w4-diagnostics\",",
    "+                  \"--dualwrite-run-label\",",
    "+                  \"20280418-w4-diag-effects-r3\",",
    "+                  \"--dualwrite-case-label\",",
    "+                  \"stream_pending_resume\",",
    "                   \"--streaming\",",
    "                   \"--stream-resume-hint\",",
    "                   \"diag-w4\",",
    "@@ -90,163 +99,27 @@",
    "                   \"8192\",",
    "                   \"/Users/dolphilia/github/kestrel/reports/dual-write/front-end/w4-diagnostics/20280418-w4-diag-effects-r3/stream_pending_resume/input.reml\"",
    "                 ],",
    "-                \"command\": \"remlc\",",
    "+                \"command\": \"target/debug/poc_frontend\",",
    "                 \"kind\": \"cli-command\"",
    "               },",
    "               {",
    "                 \"kind\": \"input\",",
    "-                \"path\": \"input.reml\",",
    "-                \"target\": \"x86_64-linux\"",
    "-              },",
    "-              {",
    "-                \"kind\": \"outputs\",",
    "-                \"values\": [",
    "-                  \"emit_parse_debug\"",
    "-                ]",
    "+                \"path\": \"/Users/dolphilia/github/kestrel/reports/dual-write/front-end/w4-diagnostics/20280418-w4-diag-effects-r3/stream_pending_resume/input.reml\",",
    "+                \"target\": \"rust-poc\"",
    "               }",
    "             ],",
    "             \"origin\": \"cli\",",
    "-            \"policy\": \"phase2.5.audit.v1\",",
    "+            \"policy\": \"rust.poc.audit.v1\",",
    "             \"source\": {",
    "-              \"build_id\": \"20251110T081149Z-d1fb623\",",
    "-              \"commit\": \"d1fb623\",",
    "-              \"sequence\": 0,",
    "-              \"workspace\": \".\"",
    "-            }",
    "-          },",
    "-          \"effect.actual_capabilities\": [],",
    "-          \"effect.capabilities\": [],",
    "-          \"effect.required_capabilities\": [],",
    "-          \"effect.stage.actual_capabilities\": [],",
    "-          \"effect.stage.required_capabilities\": [],",
    "-          \"event.domain\": \"parser\",",
    "-          \"fingerprint\": \"859967339\",",
    "-          \"name\": \"compilation_unit\",",
    "-          \"namespace\": \"menhir\",",
    "-          \"origin\": \"static\",",
    "-          \"parser\": {",
    "-            \"core\": {",
    "-              \"rule\": {",
    "-                \"fingerprint\": \"859967339\",",
    "-                \"name\": \"compilation_unit\",",
    "-                \"namespace\": \"menhir\",",
    "-                \"ordinal\": 0,",
    "-                \"origin\": \"static\"",
    "-              }",
    "-            }",
    "-          },",
    "-          \"parser.core.rule\": {",
    "-            \"fingerprint\": \"859967339\",",
    "-            \"name\": \"compilation_unit\",",
    "-            \"namespace\": \"menhir\",",
    "-            \"ordinal\": 0,",
    "-            \"origin\": \"static\"",
    "-          },",
    "-          \"parser.core.rule.fingerprint\": \"859967339\",",
    "-          \"parser.core.rule.name\": \"compilation_unit\",",
    "-          \"parser.core.rule.namespace\": \"menhir\",",
    "-          \"parser.core.rule.ordinal\": 0,",
    "-          \"parser.core.rule.origin\": \"static\",",
    "-          \"parser.runconfig\": {",
    "-            \"experimental_effects\": false,",
    "-            \"extensions\": {",
    "-              \"lex\": {",
    "-                \"identifier_profile\": \"unicode\",",
    "-                \"profile\": \"strict_json\"",
    "-              },",
    "-              \"recover\": {",
    "-                \"notes\": false,",
    "-                \"sync_tokens\": []",
    "-              },",
    "-              \"stream\": {",
    "-                \"checkpoint\": \"unspecified\",",
    "-                \"chunk_size\": 0,",
    "-                \"demand_min_bytes\": 4,",
    "-                \"demand_preferred_bytes\": 8,",
    "-                \"enabled\": true,",
    "-                \"flow\": {",
    "-                  \"backpressure\": {",
    "-                    \"max_lag_bytes\": 8192",
    "-                  },",
    "-                  \"policy\": \"auto\"",
    "-                },",
    "-                \"resume_hint\": \"diag-w4\"",
    "-              }",
    "-            },",
    "-            \"left_recursion\": \"off\",",
    "-            \"legacy_result\": true,",
    "-            \"merge_warnings\": true,",
    "-            \"packrat\": true,",
    "-            \"require_eof\": false,",
    "-            \"trace\": false",
    "-          },",
    "-          \"parser.runconfig.experimental_effects\": false,",
    "-          \"parser.runconfig.extensions.lex\": {",
    "-            \"identifier_profile\": \"unicode\",",
    "-            \"profile\": \"strict_json\"",
    "-          },",
    "-          \"parser.runconfig.extensions.lex.identifier_profile\": \"unicode\",",
    "-          \"parser.runconfig.extensions.lex.profile\": \"strict_json\",",
    "-          \"parser.runconfig.extensions.recover\": {",
    "-            \"notes\": false,",
    "-            \"sync_tokens\": []",
    "-          },",
    "-          \"parser.runconfig.extensions.recover.notes\": false,",
    "-          \"parser.runconfig.extensions.recover.sync_tokens\": [],",
    "-          \"parser.runconfig.extensions.stream\": {",
    "-            \"checkpoint\": \"unspecified\",",
    "-            \"chunk_size\": 0,",
    "-            \"demand_min_bytes\": 4,",
    "-            \"demand_preferred_bytes\": 8,",
    "-            \"enabled\": true,",
    "-            \"flow\": {",
    "-              \"backpressure\": {",
    "-                \"max_lag_bytes\": 8192",
    "-              },",
    "-              \"policy\": \"auto\"",
    "-            },",
    "-            \"resume_hint\": \"diag-w4\"",
    "-          },",
    "-          \"parser.runconfig.extensions.stream.checkpoint\": \"unspecified\",",
    "-          \"parser.runconfig.extensions.stream.chunk_size\": 0,",
    "-          \"parser.runconfig.extensions.stream.demand_min_bytes\": 4,",
    "-          \"parser.runconfig.extensions.stream.demand_preferred_bytes\": 8,",
    "-          \"parser.runconfig.extensions.stream.enabled\": true,",
    "-          \"parser.runconfig.extensions.stream.flow.backpressure.max_lag_bytes\": 8192,",
    "-          \"parser.runconfig.extensions.stream.flow.policy\": \"auto\",",
    "-          \"parser.runconfig.extensions.stream.resume_hint\": \"diag-w4\",",
    "-          \"parser.runconfig.left_recursion\": \"off\",",
    "-          \"parser.runconfig.legacy_result\": true,",
    "-          \"parser.runconfig.merge_warnings\": true,",
    "-          \"parser.runconfig.packrat\": true,",
    "-          \"parser.runconfig.require_eof\": false,",
    "-          \"parser.runconfig.trace\": false,",
    "-          \"schema.version\": \"1.1\"",
    "-        }",
    "-      },",
    "-      \"audit_metadata\": {",
    "-        \"audit.build_id\": \"20251110T081149Z-d1fb623\",",
    "-        \"audit.channel\": \"cli\",",
    "-        \"audit.policy.version\": \"phase2.5.audit.v1\",",
    "-        \"audit.sequence\": 0,",
    "-        \"audit.source.commit\": \"d1fb623\",",
    "-        \"audit.source.workspace\": \".\",",
    "-        \"audit.timestamp\": \"2025-11-10T08:11:49Z\",",
    "-        \"cli.audit_id\": \"cli/20251110T081149Z-d1fb623#0\",",
    "-        \"cli.change_set\": {",
    "-          \"items\": [",
    "-            {",
    "               \"args\": [",
    "-                \"/Users/dolphilia/github/kestrel/compiler/ocaml/_build/install/default/bin/remlc\",",
    "-                \"--packrat\",",
    "-                \"--format\",",
    "-                \"json\",",
    "-                \"--json-mode\",",
    "-                \"compact\",",
    "                 \"--emit-parse-debug\",",
    "-                \"/Users/dolphilia/github/kestrel/reports/dual-write/front-end/w4-diagnostics/20280418-w4-diag-effects-r3/stream_pending_resume/ocaml.parse-debug.json\",",
    "-                \"--left-recursion\",",
    "-                \"off\",",
    "+                \"/Users/dolphilia/github/kestrel/reports/dual-write/front-end/w4-diagnostics/20280418-w4-diag-effects-r3/stream_pending_resume/rust.parse-debug.json\",",
    "+                \"--dualwrite-root\",",
    "+                \"/Users/dolphilia/github/kestrel/reports/dual-write/front-end/w4-diagnostics\",",
    "+                \"--dualwrite-run-label\",",
    "+                \"20280418-w4-diag-effects-r3\",",
    "+                \"--dualwrite-case-label\",",
    "+                \"stream_pending_resume\",",
    "                 \"--streaming\",",
    "                 \"--stream-resume-hint\",",
    "                 \"diag-w4\",",
    "@@ -260,66 +133,251 @@",
    "                 \"8192\",",
    "                 \"/Users/dolphilia/github/kestrel/reports/dual-write/front-end/w4-diagnostics/20280418-w4-diag-effects-r3/stream_pending_resume/input.reml\"",
    "               ],",
    "-              \"command\": \"remlc\",",
    "+              \"command\": \"target/debug/poc_frontend\",",
    "+              \"workspace\": \".\"",
    "+            }",
    "+          },",
    "+          \"effect.actual_capabilities\": [],",
    "+          \"effect.required_capabilities\": [],",
    "+          \"effect.stage.actual\": \"at_least:stable\",",
    "+          \"effect.stage.actual_capabilities\": [],",
    "+          \"effect.stage.required\": \"at_least:beta\",",
    "+          \"effect.stage.required_capabilities\": [],",
    "+          \"effect.stage.trace\": [",
    "+            {",
    "+              \"note\": \"--effect-stage\",",
    "+              \"source\": \"cli_option\",",
    "+              \"stage\": \"at_least:beta\"",
    "+            },",
    "+            {",
    "+              \"source\": \"runtime\",",
    "+              \"stage\": \"at_least:stable\"",
    "+            }",
    "+          ],",
    "+          \"event.domain\": \"parser\",",
    "+          \"event.kind\": \"diagnostic\",",
    "+          \"fingerprint\": \"rust-poc-0001\",",
    "+          \"name\": \"compilation_unit\",",
    "+          \"namespace\": \"rust.poc\",",
    "+          \"origin\": \"poc_frontend\",",
    "+          \"parser.core.rule.fingerprint\": \"rust-poc-0001\",",
    "+          \"parser.core.rule.name\": \"compilation_unit\",",
    "+          \"parser.core.rule.namespace\": \"rust.poc\",",
    "+          \"parser.core.rule.ordinal\": 0,",
    "+          \"parser.core.rule.origin\": \"poc_frontend\",",
    "+          \"parser.runconfig\": {",
    "+            \"extensions\": {",
    "+              \"config\": {",
    "+                \"path\": null",
    "+              },",
    "+              \"effects\": {",
    "+                \"type_row_mode\": \"ty-integrated\"",
    "+              },",
    "+              \"lex\": {",
    "+                \"identifier_profile\": \"unicode\",",
    "+                \"profile\": \"strict_json\"",
    "+              },",
    "+              \"recover\": {",
    "+                \"notes\": false,",
    "+                \"sync_tokens\": []",
    "+              },",
    "+              \"stream\": {",
    "+                \"checkpoint\": \"unspecified\",",
    "+                \"chunk_size\": 0,",
    "+                \"demand_min_bytes\": 4,",
    "+                \"demand_preferred_bytes\": 8,",
    "+                \"enabled\": true,",
    "+                \"flow\": {",
    "+                  \"backpressure\": {",
    "+                    \"max_lag_bytes\": 8192",
    "+                  },",
    "+                  \"policy\": \"auto\"",
    "+                },",
    "+                \"flow_max_lag\": 8192,",
    "+                \"flow_policy\": \"auto\",",
    "+                \"resume_hint\": \"diag-w4\"",
    "+              }",
    "+            },",
    "+            \"runtime_capabilities\": [],",
    "+            \"switches\": {",
    "+              \"experimental_effects\": false,",
    "+              \"left_recursion\": \"off\",",
    "+              \"legacy_result\": true,",
    "+              \"merge_warnings\": true,",
    "+              \"packrat\": true,",
    "+              \"require_eof\": false,",
    "+              \"trace\": false",
    "+            }",
    "+          },",
    "+          \"parser.runconfig.extensions.lex\": {",
    "+            \"identifier_profile\": \"unicode\",",
    "+            \"profile\": \"strict_json\"",
    "+          },",
    "+          \"parser.runconfig.extensions.lex.identifier_profile\": \"unicode\",",
    "+          \"parser.runconfig.extensions.lex.profile\": \"strict_json\",",
    "+          \"parser.runconfig.extensions.recover\": {",
    "+            \"notes\": false,",
    "+            \"sync_tokens\": []",
    "+          },",
    "+          \"parser.runconfig.extensions.recover.notes\": false,",
    "+          \"parser.runconfig.extensions.recover.sync_tokens\": [],",
    "+          \"parser.runconfig.extensions.stream\": {",
    "+            \"checkpoint\": \"unspecified\",",
    "+            \"chunk_size\": 0,",
    "+            \"demand_min_bytes\": 4,",
    "+            \"demand_preferred_bytes\": 8,",
    "+            \"enabled\": true,",
    "+            \"flow\": {",
    "+              \"backpressure\": {",
    "+                \"max_lag_bytes\": 8192",
    "+              },",
    "+              \"policy\": \"auto\"",
    "+            },",
    "+            \"flow_max_lag\": 8192,",
    "+            \"flow_policy\": \"auto\",",
    "+            \"resume_hint\": \"diag-w4\"",
    "+          },",
    "+          \"parser.runconfig.extensions.stream.checkpoint\": \"unspecified\",",
    "+          \"parser.runconfig.extensions.stream.chunk_size\": 0,",
    "+          \"parser.runconfig.extensions.stream.demand_min_bytes\": 4,",
    "+          \"parser.runconfig.extensions.stream.demand_preferred_bytes\": 8,",
    "+          \"parser.runconfig.extensions.stream.enabled\": true,",
    "+          \"parser.runconfig.extensions.stream.flow.backpressure.max_lag_bytes\": 8192,",
    "+          \"parser.runconfig.extensions.stream.flow.policy\": \"auto\",",
    "+          \"parser.runconfig.extensions.stream.resume_hint\": \"diag-w4\",",
    "+          \"parser.runconfig.switches.left_recursion\": \"off\",",
    "+          \"parser.runconfig.switches.legacy_result\": true,",
    "+          \"parser.runconfig.switches.merge_warnings\": true,",
    "+          \"parser.runconfig.switches.packrat\": true,",
    "+          \"parser.runconfig.switches.require_eof\": false,",
    "+          \"parser.runconfig.switches.trace\": false,",
    "+          \"parser.stream.checkpoint\": \"unspecified\",",
    "+          \"parser.stream.demand_min_bytes\": 4,",
    "+          \"parser.stream.demand_preferred_bytes\": 8,",
    "+          \"parser.stream.flow_max_lag\": 8192,",
    "+          \"parser.stream.flow_policy\": \"auto\",",
    "+          \"parser.stream.resume_hint\": \"diag-w4\",",
    "+          \"schema.version\": \"2.0.0-draft\",",
    "+          \"stage.trace\": [",
    "+            {",
    "+              \"note\": \"--effect-stage\",",
    "+              \"source\": \"cli_option\",",
    "+              \"stage\": \"at_least:beta\"",
    "+            },",
    "+            {",
    "+              \"source\": \"runtime\",",
    "+              \"stage\": \"at_least:stable\"",
    "+            }",
    "+          ]",
    "+        }",
    "+      },",
    "+      \"audit_metadata\": {",
    "+        \"audit.channel\": \"cli\",",
    "+        \"audit.policy.version\": \"rust.poc.audit.v1\",",
    "+        \"audit.timestamp\": \"2025-11-10T08:11:49Z\",",
    "+        \"bridge.stage.actual_capabilities\": [],",
    "+        \"bridge.stage.required_capabilities\": [],",
    "+        \"capability.ids\": [],",
    "+        \"cli.audit_id\": \"cli/20251110T081149Z#0\",",
    "+        \"cli.change_set\": {",
    "+          \"items\": [",
    "+            {",
    "+              \"args\": [",
    "+                \"--emit-parse-debug\",",
    "+                \"/Users/dolphilia/github/kestrel/reports/dual-write/front-end/w4-diagnostics/20280418-w4-diag-effects-r3/stream_pending_resume/rust.parse-debug.json\",",
    "+                \"--dualwrite-root\",",
    "+                \"/Users/dolphilia/github/kestrel/reports/dual-write/front-end/w4-diagnostics\",",
    "+                \"--dualwrite-run-label\",",
    "+                \"20280418-w4-diag-effects-r3\",",
    "+                \"--dualwrite-case-label\",",
    "+                \"stream_pending_resume\",",
    "+                \"--streaming\",",
    "+                \"--stream-resume-hint\",",
    "+                \"diag-w4\",",
    "+                \"--stream-flow-policy\",",
    "+                \"auto\",",
    "+                \"--stream-demand-min-bytes\",",
    "+                \"4\",",
    "+                \"--stream-demand-preferred-bytes\",",
    "+                \"8\",",
    "+                \"--stream-flow-max-lag\",",
    "+                \"8192\",",
    "+                \"/Users/dolphilia/github/kestrel/reports/dual-write/front-end/w4-diagnostics/20280418-w4-diag-effects-r3/stream_pending_resume/input.reml\"",
    "+              ],",
    "+              \"command\": \"target/debug/poc_frontend\",",
    "               \"kind\": \"cli-command\"",
    "             },",
    "             {",
    "               \"kind\": \"input\",",
    "-              \"path\": \"input.reml\",",
    "-              \"target\": \"x86_64-linux\"",
    "-            },",
    "-            {",
    "-              \"kind\": \"outputs\",",
    "-              \"values\": [",
    "-                \"emit_parse_debug\"",
    "-              ]",
    "+              \"path\": \"/Users/dolphilia/github/kestrel/reports/dual-write/front-end/w4-diagnostics/20280418-w4-diag-effects-r3/stream_pending_resume/input.reml\",",
    "+              \"target\": \"rust-poc\"",
    "             }",
    "           ],",
    "           \"origin\": \"cli\",",
    "-          \"policy\": \"phase2.5.audit.v1\",",
    "+          \"policy\": \"rust.poc.audit.v1\",",
    "           \"source\": {",
    "-            \"build_id\": \"20251110T081149Z-d1fb623\",",
    "-            \"commit\": \"d1fb623\",",
    "-            \"sequence\": 0,",
    "+            \"args\": [",
    "+              \"--emit-parse-debug\",",
    "+              \"/Users/dolphilia/github/kestrel/reports/dual-write/front-end/w4-diagnostics/20280418-w4-diag-effects-r3/stream_pending_resume/rust.parse-debug.json\",",
    "+              \"--dualwrite-root\",",
    "+              \"/Users/dolphilia/github/kestrel/reports/dual-write/front-end/w4-diagnostics\",",
    "+              \"--dualwrite-run-label\",",
    "+              \"20280418-w4-diag-effects-r3\",",
    "+              \"--dualwrite-case-label\",",
    "+              \"stream_pending_resume\",",
    "+              \"--streaming\",",
    "+              \"--stream-resume-hint\",",
    "+              \"diag-w4\",",
    "+              \"--stream-flow-policy\",",
    "+              \"auto\",",
    "+              \"--stream-demand-min-bytes\",",
    "+              \"4\",",
    "+              \"--stream-demand-preferred-bytes\",",
    "+              \"8\",",
    "+              \"--stream-flow-max-lag\",",
    "+              \"8192\",",
    "+              \"/Users/dolphilia/github/kestrel/reports/dual-write/front-end/w4-diagnostics/20280418-w4-diag-effects-r3/stream_pending_resume/input.reml\"",
    "+            ],",
    "+            \"command\": \"target/debug/poc_frontend\",",
    "             \"workspace\": \".\"",
    "           }",
    "         },",
    "         \"effect.actual_capabilities\": [],",
    "-        \"effect.capabilities\": [],",
    "         \"effect.required_capabilities\": [],",
    "+        \"effect.stage.actual\": \"at_least:stable\",",
    "         \"effect.stage.actual_capabilities\": [],",
    "+        \"effect.stage.required\": \"at_least:beta\",",
    "         \"effect.stage.required_capabilities\": [],",
    "+        \"effect.stage.trace\": [",
    "+          {",
    "+            \"note\": \"--effect-stage\",",
    "+            \"source\": \"cli_option\",",
    "+            \"stage\": \"at_least:beta\"",
    "+          },",
    "+          {",
    "+            \"source\": \"runtime\",",
    "+            \"stage\": \"at_least:stable\"",
    "+          }",
    "+        ],",
    "         \"event.domain\": \"parser\",",
    "-        \"fingerprint\": \"859967339\",",
    "+        \"event.kind\": \"diagnostic\",",
    "+        \"fingerprint\": \"rust-poc-0001\",",
    "         \"name\": \"compilation_unit\",",
    "-        \"namespace\": \"menhir\",",
    "-        \"origin\": \"static\",",
    "-        \"parser\": {",
    "-          \"core\": {",
    "-            \"rule\": {",
    "-              \"fingerprint\": \"859967339\",",
    "-              \"name\": \"compilation_unit\",",
    "-              \"namespace\": \"menhir\",",
    "-              \"ordinal\": 0,",
    "-              \"origin\": \"static\"",
    "-            }",
    "-          }",
    "-        },",
    "-        \"parser.core.rule\": {",
    "-          \"fingerprint\": \"859967339\",",
    "-          \"name\": \"compilation_unit\",",
    "-          \"namespace\": \"menhir\",",
    "-          \"ordinal\": 0,",
    "-          \"origin\": \"static\"",
    "-        },",
    "-        \"parser.core.rule.fingerprint\": \"859967339\",",
    "+        \"namespace\": \"rust.poc\",",
    "+        \"origin\": \"poc_frontend\",",
    "+        \"parser.core.rule.fingerprint\": \"rust-poc-0001\",",
    "         \"parser.core.rule.name\": \"compilation_unit\",",
    "-        \"parser.core.rule.namespace\": \"menhir\",",
    "+        \"parser.core.rule.namespace\": \"rust.poc\",",
    "         \"parser.core.rule.ordinal\": 0,",
    "-        \"parser.core.rule.origin\": \"static\",",
    "+        \"parser.core.rule.origin\": \"poc_frontend\",",
    "         \"parser.runconfig\": {",
    "-          \"experimental_effects\": false,",
    "           \"extensions\": {",
    "+            \"config\": {",
    "+              \"path\": null",
    "+            },",
    "+            \"effects\": {",
    "+              \"type_row_mode\": \"ty-integrated\"",
    "+            },",
    "             \"lex\": {",
    "               \"identifier_profile\": \"unicode\",",
    "               \"profile\": \"strict_json\"",
    "@@ -340,17 +398,22 @@",
    "                 },",
    "                 \"policy\": \"auto\"",
    "               },",
    "+              \"flow_max_lag\": 8192,",
    "+              \"flow_policy\": \"auto\",",
    "               \"resume_hint\": \"diag-w4\"",
    "             }",
    "           },",
    "-          \"left_recursion\": \"off\",",
    "-          \"legacy_result\": true,",
    "-          \"merge_warnings\": true,",
    "-          \"packrat\": true,",
    "-          \"require_eof\": false,",
    "-          \"trace\": false",
    "-        },",
    "-        \"parser.runconfig.experimental_effects\": false,",
    "+          \"runtime_capabilities\": [],",
    "+          \"switches\": {",
    "+            \"experimental_effects\": false,",
    "+            \"left_recursion\": \"off\",",
    "+            \"legacy_result\": true,",
    "+            \"merge_warnings\": true,",
    "+            \"packrat\": true,",
    "+            \"require_eof\": false,",
    "+            \"trace\": false",
    "+          }",
    "+        },",
    "         \"parser.runconfig.extensions.lex\": {",
    "           \"identifier_profile\": \"unicode\",",
    "           \"profile\": \"strict_json\"",
    "@@ -375,6 +438,8 @@",
    "             },",
    "             \"policy\": \"auto\"",
    "           },",
    "+          \"flow_max_lag\": 8192,",
    "+          \"flow_policy\": \"auto\",",
    "           \"resume_hint\": \"diag-w4\"",
    "         },",
    "         \"parser.runconfig.extensions.stream.checkpoint\": \"unspecified\",",
    "@@ -385,288 +450,83 @@",
    "         \"parser.runconfig.extensions.stream.flow.backpressure.max_lag_bytes\": 8192,",
    "         \"parser.runconfig.extensions.stream.flow.policy\": \"auto\",",
    "         \"parser.runconfig.extensions.stream.resume_hint\": \"diag-w4\",",
    "-        \"parser.runconfig.left_recursion\": \"off\",",
    "-        \"parser.runconfig.legacy_result\": true,",
    "-        \"parser.runconfig.merge_warnings\": true,",
    "-        \"parser.runconfig.packrat\": true,",
    "-        \"parser.runconfig.require_eof\": false,",
    "-        \"parser.runconfig.trace\": false,",
    "-        \"schema.version\": \"1.1\"",
    "-      },",
    "+        \"parser.runconfig.switches.left_recursion\": \"off\",",
    "+        \"parser.runconfig.switches.legacy_result\": true,",
    "+        \"parser.runconfig.switches.merge_warnings\": true,",
    "+        \"parser.runconfig.switches.packrat\": true,",
    "+        \"parser.runconfig.switches.require_eof\": false,",
    "+        \"parser.runconfig.switches.trace\": false,",
    "+        \"parser.stream.checkpoint\": \"unspecified\",",
    "+        \"parser.stream.demand_min_bytes\": 4,",
    "+        \"parser.stream.demand_preferred_bytes\": 8,",
    "+        \"parser.stream.flow_max_lag\": 8192,",
    "+        \"parser.stream.flow_policy\": \"auto\",",
    "+        \"parser.stream.resume_hint\": \"diag-w4\",",
    "+        \"schema.version\": \"2.0.0-draft\",",
    "+        \"stage.trace\": [",
    "+          {",
    "+            \"note\": \"--effect-stage\",",
    "+            \"source\": \"cli_option\",",
    "+            \"stage\": \"at_least:beta\"",
    "+          },",
    "+          {",
    "+            \"source\": \"runtime\",",
    "+            \"stage\": \"at_least:stable\"",
    "+          }",
    "+        ]",
    "+      },",
    "+      \"code\": null,",
    "       \"domain\": \"parser\",",
    "       \"expected\": {",
    "         \"alternatives\": [",
    "           {",
    "             \"kind\": \"keyword\",",
    "-            \"value\": \"continue\"",
    "-          },",
    "-          {",
    "-            \"kind\": \"keyword\",",
    "-            \"value\": \"defer\"",
    "-          },",
    "-          {",
    "-            \"kind\": \"keyword\",",
    "-            \"value\": \"do\"",
    "-          },",
    "-          {",
    "-            \"kind\": \"keyword\",",
    "-            \"value\": \"false\"",
    "-          },",
    "-          {",
    "-            \"kind\": \"keyword\",",
    "-            \"value\": \"for\"",
    "-          },",
    "-          {",
    "-            \"kind\": \"keyword\",",
    "-            \"value\": \"handle\"",
    "-          },",
    "-          {",
    "-            \"kind\": \"keyword\",",
    "-            \"value\": \"if\"",
    "-          },",
    "-          {",
    "-            \"kind\": \"keyword\",",
    "-            \"value\": \"loop\"",
    "-          },",
    "-          {",
    "-            \"kind\": \"keyword\",",
    "-            \"value\": \"match\"",
    "-          },",
    "-          {",
    "-            \"kind\": \"keyword\",",
    "-            \"value\": \"perform\"",
    "-          },",
    "-          {",
    "-            \"kind\": \"keyword\",",
    "-            \"value\": \"return\"",
    "-          },",
    "-          {",
    "-            \"kind\": \"keyword\",",
    "-            \"value\": \"self\"",
    "-          },",
    "-          {",
    "-            \"kind\": \"keyword\",",
    "-            \"value\": \"true\"",
    "-          },",
    "-          {",
    "-            \"kind\": \"keyword\",",
    "-            \"value\": \"unsafe\"",
    "-          },",
    "-          {",
    "-            \"kind\": \"keyword\",",
    "-            \"value\": \"while\"",
    "-          },",
    "-          {",
    "-            \"kind\": \"token\",",
    "-            \"value\": \"!\"",
    "-          },",
    "-          {",
    "-            \"kind\": \"token\",",
    "-            \"value\": \"(\"",
    "-          },",
    "-          {",
    "-            \"kind\": \"token\",",
    "-            \"value\": \"-\"",
    "-          },",
    "-          {",
    "-            \"kind\": \"token\",",
    "-            \"value\": \"[\"",
    "-          },",
    "-          {",
    "-            \"kind\": \"token\",",
    "-            \"value\": \"{\"",
    "-          },",
    "-          {",
    "-            \"kind\": \"token\",",
    "-            \"value\": \"|\"",
    "-          },",
    "-          {",
    "-            \"kind\": \"class\",",
    "-            \"value\": \"char-literal\"",
    "-          },",
    "-          {",
    "-            \"kind\": \"class\",",
    "-            \"value\": \"float-literal\"",
    "-          },",
    "-          {",
    "-            \"kind\": \"class\",",
    "-            \"value\": \"identifier\"",
    "-          },",
    "-          {",
    "-            \"kind\": \"class\",",
    "-            \"value\": \"integer-literal\"",
    "-          },",
    "-          {",
    "-            \"kind\": \"class\",",
    "-            \"value\": \"string-literal\"",
    "-          },",
    "-          {",
    "-            \"kind\": \"class\",",
    "-            \"value\": \"upper-identifier\"",
    "+            \"label\": \"fn\"",
    "           }",
    "         ],",
    "-        \"humanized\": \"ここで`continue`、`defer`、`do`、`false`、`for`、`handle`、`if`、`loop`、`match`、`perform`、`return`、`self`、`true`、`unsafe`、`while`、`!`、`(`、`-`、`[`、`{`、`|`、char-literal、float-literal、identifier、integer-literal、string-literal または upper-identifierのいずれかが必要です\",",
    "+        \"humanized\": \"ここで`fn`が必要です\",",
    "         \"locale_args\": [",
    "-          \"continue\",",
    "-          \"defer\",",
    "-          \"do\",",
    "-          \"false\",",
    "-          \"for\",",
    "-          \"handle\",",
    "-          \"if\",",
    "-          \"loop\",",
    "-          \"match\",",
    "-          \"perform\",",
    "-          \"return\",",
    "-          \"self\",",
    "-          \"true\",",
    "-          \"unsafe\",",
    "-          \"while\",",
    "-          \"!\",",
    "-          \"(\",",
    "-          \"-\",",
    "-          \"[\",",
    "-          \"{\",",
    "-          \"|\",",
    "-          \"char-literal\",",
    "-          \"float-literal\",",
    "-          \"identifier\",",
    "-          \"integer-literal\",",
    "-          \"string-literal\",",
    "-          \"upper-identifier\"",
    "+          \"fn\"",
    "         ],",
    "         \"message_key\": \"parse.expected\"",
    "       },",
    "       \"extensions\": {",
    "+        \"capability\": {",
    "+          \"detail\": [],",
    "+          \"ids\": [],",
    "+          \"required_capabilities\": [],",
    "+          \"stage\": {",
    "+            \"actual\": \"at_least:stable\",",
    "+            \"required\": \"at_least:beta\"",
    "+          }",
    "+        },",
    "         \"diagnostic.v2\": {",
    "           \"timestamp\": \"2025-11-10T08:11:49Z\"",
    "         },",
    "         \"effect.actual_capabilities\": [],",
    "         \"effect.capabilities\": [],",
    "         \"effect.required_capabilities\": [],",
    "+        \"effect.stage.actual\": \"at_least:stable\",",
    "         \"effect.stage.actual_capabilities\": [],",
    "+        \"effect.stage.required\": \"at_least:beta\",",
    "         \"effect.stage.required_capabilities\": [],",
    "         \"parse\": {",
    "           \"parser_id\": {",
    "-            \"fingerprint\": \"859967339\",",
    "+            \"fingerprint\": \"rust-poc-0001\",",
    "             \"name\": \"compilation_unit\",",
    "-            \"namespace\": \"menhir\",",
    "+            \"namespace\": \"rust.poc\",",
    "             \"ordinal\": 0,",
    "-            \"origin\": \"static\"",
    "+            \"origin\": \"poc_frontend\"",
    "           }",
    "         },",
    "         \"recover\": {",
    "           \"expected_tokens\": [",
    "             {",
    "               \"kind\": \"keyword\",",
    "-              \"label\": \"continue\"",
    "-            },",
    "-            {",
    "-              \"kind\": \"keyword\",",
    "-              \"label\": \"defer\"",
    "-            },",
    "-            {",
    "-              \"kind\": \"keyword\",",
    "-              \"label\": \"do\"",
    "-            },",
    "-            {",
    "-              \"kind\": \"keyword\",",
    "-              \"label\": \"false\"",
    "-            },",
    "-            {",
    "-              \"kind\": \"keyword\",",
    "-              \"label\": \"for\"",
    "-            },",
    "-            {",
    "-              \"kind\": \"keyword\",",
    "-              \"label\": \"handle\"",
    "-            },",
    "-            {",
    "-              \"kind\": \"keyword\",",
    "-              \"label\": \"if\"",
    "-            },",
    "-            {",
    "-              \"kind\": \"keyword\",",
    "-              \"label\": \"loop\"",
    "-            },",
    "-            {",
    "-              \"kind\": \"keyword\",",
    "-              \"label\": \"match\"",
    "-            },",
    "-            {",
    "-              \"kind\": \"keyword\",",
    "-              \"label\": \"perform\"",
    "-            },",
    "-            {",
    "-              \"kind\": \"keyword\",",
    "-              \"label\": \"return\"",
    "-            },",
    "-            {",
    "-              \"kind\": \"keyword\",",
    "-              \"label\": \"self\"",
    "-            },",
    "-            {",
    "-              \"kind\": \"keyword\",",
    "-              \"label\": \"true\"",
    "-            },",
    "-            {",
    "-              \"kind\": \"keyword\",",
    "-              \"label\": \"unsafe\"",
    "-            },",
    "-            {",
    "-              \"kind\": \"keyword\",",
    "-              \"label\": \"while\"",
    "-            },",
    "-            {",
    "-              \"kind\": \"token\",",
    "-              \"label\": \"!\"",
    "-            },",
    "-            {",
    "-              \"kind\": \"token\",",
    "-              \"label\": \"(\"",
    "-            },",
    "-            {",
    "-              \"kind\": \"token\",",
    "-              \"label\": \"-\"",
    "-            },",
    "-            {",
    "-              \"kind\": \"token\",",
    "-              \"label\": \"[\"",
    "-            },",
    "-            {",
    "-              \"kind\": \"token\",",
    "-              \"label\": \"{\"",
    "-            },",
    "-            {",
    "-              \"kind\": \"token\",",
    "-              \"label\": \"|\"",
    "-            },",
    "-            {",
    "-              \"kind\": \"class\",",
    "-              \"label\": \"char-literal\"",
    "-            },",
    "-            {",
    "-              \"kind\": \"class\",",
    "-              \"label\": \"float-literal\"",
    "-            },",
    "-            {",
    "-              \"kind\": \"class\",",
    "-              \"label\": \"identifier\"",
    "-            },",
    "-            {",
    "-              \"kind\": \"class\",",
    "-              \"label\": \"integer-literal\"",
    "-            },",
    "-            {",
    "-              \"kind\": \"class\",",
    "-              \"label\": \"string-literal\"",
    "-            },",
    "-            {",
    "-              \"kind\": \"class\",",
    "-              \"label\": \"upper-identifier\"",
    "+              \"label\": \"fn\"",
    "             }",
    "           ],",
    "-          \"message\": \"ここで`continue`、`defer`、`do`、`false`、`for`、`handle`、`if`、`loop`、`match`、`perform`、`return`、`self`、`true`、`unsafe`、`while`、`!`、`(`、`-`、`[`、`{`、`|`、char-literal、float-literal、identifier、integer-literal、string-literal または upper-identifierのいずれかが必要です\"",
    "+          \"message\": \"ここで`fn`が必要です\"",
    "         },",
    "         \"runconfig\": {",
    "           \"experimental_effects\": false,",
    "@@ -691,6 +551,8 @@",
    "                 },",
    "                 \"policy\": \"auto\"",
    "               },",
    "+              \"flow_max_lag\": 8192,",
    "+              \"flow_policy\": \"auto\",",
    "               \"resume_hint\": \"diag-w4\"",
    "             }",
    "           },",
    "@@ -703,16 +565,104 @@",
    "         }",
    "       },",
    "       \"location\": {",
    "-        \"column\": 15,",
    "-        \"endColumn\": 16,",
    "-        \"endLine\": 3,",
    "+        \"column\": 1,",
    "+        \"endColumn\": 7,",
    "+        \"endLine\": 1,",
    "         \"file\": \"/Users/dolphilia/github/kestrel/reports/dual-write/front-end/w4-diagnostics/20280418-w4-diag-effects-r3/stream_pending_resume/input.reml\",",
    "-        \"line\": 3",
    "-      },",
    "-      \"message\": \"Unexpected character: \\\\\",",
    "+        \"line\": 1",
    "+      },",
    "+      \"message\": \"構文エラー: 入力を解釈できません\",",
    "+      \"notes\": [",
    "+        {",
    "+          \"label\": \"recover.expected_tokens\",",
    "+          \"message\": \"ここで`fn`が必要です\",",
    "+          \"span\": null",
    "+        }",
    "+      ],",
    "+      \"recoverability\": \"recoverable\",",
    "       \"schema_version\": \"2.0.0-draft\",",
    "       \"severity\": \"error\",",
    "       \"timestamp\": \"2025-11-10T08:11:49Z\"",
    "     }",
    "-  ]",
    "+  ],",
    "+  \"input\": \"/Users/dolphilia/github/kestrel/reports/dual-write/front-end/w4-diagnostics/20280418-w4-diag-effects-r3/stream_pending_resume/input.reml\",",
    "+  \"parse_result\": {",
    "+    \"packrat_stats\": {",
    "+      \"approx_bytes\": 283,",
    "+      \"budget_drops\": 0,",
    "+      \"entries\": 1,",
    "+      \"evictions\": 0,",
    "+      \"hits\": 6,",
    "+      \"pruned\": 0,",
    "+      \"queries\": 7",
    "+    },",
    "+    \"span_trace\": [",
    "+      {",
    "+        \"label\": \"parser.simple_error\",",
    "+        \"span\": {",
    "+          \"end\": 6,",
    "+          \"start\": 0",
    "+        }",
    "+      }",
    "+    ]",
    "+  },",
    "+  \"run_config\": {",
    "+    \"extensions\": {",
    "+      \"config\": {",
    "+        \"path\": null",
    "+      },",
    "+      \"effects\": {",
    "+        \"type_row_mode\": \"ty-integrated\"",
    "+      },",
    "+      \"lex\": {",
    "+        \"identifier_profile\": \"unicode\",",
    "+        \"profile\": \"strict_json\"",
    "+      },",
    "+      \"recover\": {",
    "+        \"notes\": false,",
    "+        \"sync_tokens\": []",
    "+      },",
    "+      \"stream\": {",
    "+        \"checkpoint\": \"unspecified\",",
    "+        \"chunk_size\": 0,",
    "+        \"demand_min_bytes\": 4,",
    "+        \"demand_preferred_bytes\": 8,",
    "+        \"enabled\": true,",
    "+        \"flow\": {",
    "+          \"backpressure\": {",
    "+            \"max_lag_bytes\": 8192",
    "+          },",
    "+          \"policy\": \"auto\"",
    "+        },",
    "+        \"flow_max_lag\": 8192,",
    "+        \"flow_policy\": \"auto\",",
    "+        \"resume_hint\": \"diag-w4\"",
    "+      }",
    "+    },",
    "+    \"runtime_capabilities\": [],",
    "+    \"switches\": {",
    "+      \"experimental_effects\": false,",
    "+      \"left_recursion\": \"off\",",
    "+      \"legacy_result\": true,",
    "+      \"merge_warnings\": true,",
    "+      \"packrat\": true,",
    "+      \"require_eof\": false,",
    "+      \"trace\": false",
    "+    }",
    "+  },",
    "+  \"stream_meta\": {",
    "+    \"packrat\": {",
    "+      \"approx_bytes\": 283,",
    "+      \"budget_drops\": 0,",
    "+      \"entries\": 1,",
    "+      \"evictions\": 0,",
    "+      \"hits\": 6,",
    "+      \"pruned\": 0,",
    "+      \"queries\": 7",
    "+    },",
    "+    \"span_trace\": {",
    "+      \"dropped\": 0,",
    "+      \"retained\": 1",
    "+    }",
    "+  }",
    " }"
  ],
  "delta": 1086
}